{
  "name" : "Canopy Spider",
  "imageUrls" : {
    "lowResolution" : "https://img.scryfall.com/cards/normal/front/0/a/0ae7fabb-dcb6-4c21-87ee-2893b63814be.jpg?1563900464",
    "highResolution" : "https://img.scryfall.com/cards/png/front/0/a/0ae7fabb-dcb6-4c21-87ee-2893b63814be.png?1563900464"
  },
  "colors" : [ "GREEN" ],
  "cost" : [ "GREEN", "COLORLESS" ],
  "types" : [ "CREATURE" ],
  "subtypes" : [ "SPIDER" ],
  "rarity" : "COMMON",
  "power" : 1,
  "toughness" : 3,
  "abilities" : [ {
    "abilityType" : "REACH"
  } ]
}