{
  "name": "Mark of the Vampire",
  "colors": [
    "BLACK"
  ],
  "cost": [
    "BLACK",
    "COLORLESS",
    "COLORLESS",
    "COLORLESS"
  ],
  "types": [
    "ENCHANTMENT"
  ],
  "subtypes": [
    "AURA"
  ],
  "rarity": "COMMON",
  "ruleText": "Enchant creature. Enchanted creature gets +2/+2 and has lifelink.",
  "abilities": [
    {
      "abilityType": "ENCHANTED_CREATURE_GETS",
      "targets": [
        {
          "cardInstanceSelector": {
            "selectorType": "PERMANENT",
            "ofType": [
              "CREATURE"
            ]
          }
        }
      ],
      "parameters": [
        "+2/+2",
        "LIFELINK"
      ],
      "trigger": {
        "type": "CAST"
      }
    }
  ]
}