{
  "name" : "Strider Harness",
  "imageUrl" : "https://img.scryfall.com/cards/png/front/5/e/5e94daa9-5b9b-4fd2-829e-081eed22c18f.png?1555041055",
  "cost" : [ "COLORLESS", "COLORLESS", "COLORLESS" ],
  "types" : [ "ARTIFACT" ],
  "subtypes" : [ "EQUIPMENT" ],
  "rarity" : "COMMON",
  "ruleText" : "Equipped creature gets +1/+1 and has haste. Equip 1",
  "abilities" : [ {
    "abilityType" : "EQUIPPED_CREATURE_GETS",
    "targets" : [ {
      "cardInstanceSelector" : {
        "selectorType" : "PERMANENT",
        "ofType" : [ "CREATURE" ]
      }
    } ],
    "parameters" : [ "+1/+1", "HASTE" ],
    "trigger" : {
      "type" : "ACTIVATED_ABILITY",
      "cost" : [ "COLORLESS" ]
    }
  } ]
}